biorosetta/__init__.py
biorosetta/classes.py
biorosetta/queries.py
biorosetta/utils.py
biorosetta-0.3.2.dist-info/LICENSE
biorosetta-0.3.2.dist-info/METADATA
biorosetta-0.3.2.dist-info/WHEEL
biorosetta-0.3.2.dist-info/top_level.txt
biorosetta-0.3.2.dist-info/RECORD
