Metadata-Version: 2.1
Name: biorosetta
Version: 0.3.2
Summary: A package to convert gene identifiers between different naming conventions
Home-page: https://github.com/reemagit/biorosetta
Author: Enrico Maiorino
Author-email: enrico.maiorino@gmail.com
License-File: LICENSE
Requires-Dist: biothings-client
Requires-Dist: tqdm
Requires-Dist: pandas
